[
  {
    "slug": "schaper-daux",
    "name": "SchaperDaux",
    "subtitle": "B2B-Outreach Starter — Stickerei & Druckerei",
    "type": "offer",
    "secure": "7341826509",
    "icon": "🧵",
    "created": "2026-03-20"
  },
  {
    "slug": "home-of-jobs",
    "name": "home of jobs",
    "subtitle": "Planbare Erstgespräche für home of jobs — Sales Room",
    "type": "sales-room",
    "secure": "7391824560",
    "icon": "🏠",
    "created": "2026-03-17"
  },
  {
    "slug": "meow-berlin",
    "name": "Meow Berlin",
    "subtitle": "Planbare Buchungen — Sales Room",
    "type": "sales-room",
    "secure": "5525281406",
    "icon": "🐱",
    "created": "2026-03-16"
  },
  {
    "slug": "kunststoff-vision",
    "name": "kunststoff.vision",
    "subtitle": "LinkedIn Branchenbotschafter — Sales Room",
    "type": "sales-room",
    "secure": "7364128905",
    "icon": "⚙️",
    "created": "2026-03-25"
  },
  {
    "slug": "das-schaffenswerk",
    "name": "Das Schaffenswerk",
    "subtitle": "Filmproduktion München — Lead-Paket + Monatliche Optionen",
    "type": "offer",
    "secure": "7364920851",
    "icon": "🎬",
    "created": "2026-03-16"
  },
  {
    "slug": "iceage-media",
    "name": "Iceage Media",
    "subtitle": "100 Leads — Sales Room",
    "type": "sales-room",
    "secure": "7493826150",
    "icon": "I",
    "created": "2026-03-16"
  },
  {
    "slug": "elitec-ag-room",
    "name": "elitec AG",
    "subtitle": "Sales Room v2 — Rebuild",
    "type": "sales-room",
    "secure": "7391582064",
    "icon": "E",
    "created": "2026-03-15"
  },
  {
    "slug": "buchner-partner",
    "name": "Buchner & Partner GmbH",
    "subtitle": "Neue Teilnehmer für dein Praxisforum",
    "type": "offer",
    "secure": "5937264810",
    "icon": "B",
    "created": "2026-03-15"
  },
  {
    "slug": "template-v1",
    "name": "Sales Room Template",
    "subtitle": "V1.0 — Basis-Template",
    "type": "template",
    "secure": "0000000000",
    "icon": "T",
    "created": "2026-03-15"
  },
  {
    "slug": "urbify",
    "name": "Urbify",
    "subtitle": "Sales Room",
    "type": "sales-room",
    "secure": "7294830165",
    "icon": "U",
    "created": "2026-03-10"
  },
  {
    "slug": "urbify-sr",
    "name": "Urbify",
    "subtitle": "Sales Room (ohne Angebot)",
    "type": "sales-room",
    "secure": "7294830165",
    "icon": "U",
    "created": "2026-03-15"
  },
  {
    "slug": "elitec-ag",
    "name": "elitec AG",
    "subtitle": "Planbare Neukunden",
    "type": "offer",
    "secure": "4827193056",
    "icon": "E",
    "created": "2026-03-05"
  },
  {
    "slug": "Starqstrom",
    "name": "STARQstrom",
    "subtitle": "Planbare B2B-Leads",
    "type": "offer",
    "secure": "7364912058",
    "icon": "S",
    "created": "2026-03-01"
  },
  {
    "slug": "digirehab",
    "name": "DigiRehab GmbH",
    "subtitle": "Sales Room — Digitale Reha für ambulante Praxen",
    "type": "sales-room",
    "secure": "7284916350",
    "icon": "🏥",
    "created": "2026-03-16"
  },
  {
    "slug": "18a-studio",
    "name": "18a.studio",
    "subtitle": "Angebot",
    "type": "offer",
    "secure": "6984172496",
    "icon": "18",
    "created": "2026-02-20"
  },
  {
    "slug": "misterneo",
    "name": "MisterNeo",
    "subtitle": "Planbare B2B-Teamevent-Buchungen — Sales Room",
    "type": "sales-room",
    "secure": "7364918250",
    "icon": "🎯",
    "created": "2026-03-23"
  },
  {
    "slug": "paul-reber",
    "name": "Paul Reber GmbH",
    "subtitle": "Blueprint Kampagne — 2.000 Entscheider",
    "type": "offer",
    "secure": "7263048519",
    "icon": "🍫",
    "created": "2026-03-16"
  },
  {
    "slug": "time-connect",
    "name": "T.I.M.E. connect",
    "subtitle": "Oktoberfest Tischreservierungen — 100 Anfragen",
    "type": "sales-room",
    "secure": "9113086612",
    "icon": "🎪",
    "created": "2026-03-17"
  },
  {
    "slug": "make-a-design",
    "name": "Make a Design GmbH",
    "subtitle": "80 Leads Garantie — Sales Room",
    "type": "sales-room",
    "secure": "7395841026",
    "icon": "🎨",
    "created": "2026-03-17"
  },
  {
    "slug": "falcondev",
    "name": "falconDev IT GmbH",
    "subtitle": "60 Leads Paket Gesundheitswesen",
    "type": "offer",
    "secure": "7391504826",
    "icon": "🏥",
    "created": "2026-03-19"
  },
  {
    "slug": "pure-perfection",
    "name": "Pure Perfection GmbH",
    "subtitle": "E-Mail Outreach DAX/MDAX Entscheider",
    "type": "offer",
    "secure": "7316284950",
    "icon": "🎪",
    "created": "2026-03-21"
  },
  {
    "slug": "creakom",
    "name": "Creakom Business Solutions",
    "subtitle": "Joseph Schoengruber — CRM, Events, Digitalisierung",
    "type": "offer",
    "secure": "7263918450",
    "icon": "🖥️",
    "created": "2026-03-22"
  },
  {
    "slug": "kintlein-ose",
    "name": "KINTLEIN & OSE GMBH & CO. KG",
    "subtitle": "Marcus Raschke — Solaranlagenbau, Neue Bundesländer",
    "type": "offer",
    "secure": "7364918205",
    "icon": "☀️",
    "created": "2026-03-23"
  }
]